jupyterhub_jwtauthenticator-0.1.dist-info/DESCRIPTION.rst
jupyterhub_jwtauthenticator-0.1.dist-info/METADATA
jupyterhub_jwtauthenticator-0.1.dist-info/RECORD
jupyterhub_jwtauthenticator-0.1.dist-info/WHEEL
jupyterhub_jwtauthenticator-0.1.dist-info/metadata.json
jupyterhub_jwtauthenticator-0.1.dist-info/top_level.txt
jwtauthenticator/__init__.py
jwtauthenticator/jwtauthenticator.py
