Metadata-Version: 2.0
Name: jupyterhub-jwtauthenticator
Version: 0.1
Summary: JSONWebToken Authenticator for JupyterHub
Home-page: https://github.com/mogthesprog/jwtauthenticator
Author: mogthesprog
Author-email: mevanj89@gmail.com
License: Apache 2.0
Platform: UNKNOWN
Requires-Dist: jupyterhub
Requires-Dist: python-jose
